<Properties StartupConfiguration="{C865CA73-E20E-46C2-8775-B8F58C251CC6}|SuperMarketManagement">
  <MonoDevelop.Ide.Workbench>
    <Pads>
      <Pad Id="ProjectPad">
        <State name="__root__">
          <Node name="SuperMarketManagement" expanded="True">
            <Node name="WebApp" expanded="True">
              <Node name="Areas" expanded="True">
                <Node name="Identity" expanded="True">
                  <Node name="Pages" expanded="True">
                    <Node name="Account" expanded="True" />
                    <Node name="_ViewImports.cshtml" selected="True" />
                  </Node>
                </Node>
              </Node>
              <Node name="Controls" expanded="True" />
              <Node name="Pages" expanded="True">
                <Node name="Shared" expanded="True" />
              </Node>
              <Node name="appsettings.json" expanded="True" />
            </Node>
          </Node>
        </State>
      </Pad>
      <Pad Id="MonoDevelop.Debugger.WatchPad">
        <State />
      </Pad>
    </Pads>
  </MonoDevelop.Ide.Workbench>
  <MonoDevelop.Ide.ItemProperties.WebApp PreferredExecutionTarget="/Applications/Safari.app" />
  <MonoDevelop.Ide.DebuggingService.PinnedWatches />
  <MonoDevelop.Ide.Workspace ActiveConfiguration="Debug" />
  <MonoDevelop.Ide.DebuggingService.Breakpoints>
    <BreakpointStore>
      <Breakpoint file="/Users/azizbekboboyev/Developer/vscode/webproj/SuperMarketManagement/WebApp/Areas/Identity/Pages/Account/_ViewImports.cshtml" relfile="WebApp/Areas/Identity/Pages/Account/_ViewImports.cshtml" line="1" column="1" />
    </BreakpointStore>
  </MonoDevelop.Ide.DebuggingService.Breakpoints>
  <MultiItemStartupConfigurations />
</Properties>